{
  "project_info": {
    "project_number": "406572393086",
    "project_id": "hconnect-bcf99",
    "storage_bucket": "hconnect-bcf99.appspot.com"
  },
  "client": [
    {
      "client_info": {
        "mobilesdk_app_id": "1:406572393086:android:4c81212b28487d44f3ee2f",
        "android_client_info": {
          "package_name": "com.example.hconnect"
        }
      },
      "oauth_client": [
        {
          "client_id": "406572393086-d0k5cupq85cnlfheffj76a1lpvrm16rf.apps.googleusercontent.com",
          "client_type": 1,
          "android_info": {
            "package_name": "com.example.hconnect",
            "certificate_hash": "a202a3486941baa8df42d3f043d5adb74d29d702"
          }
        },
        {
          "client_id": "406572393086-j2mj3etu74timpbje8gathv8ggl7bnek.apps.googleusercontent.com",
          "client_type": 3
        }
      ],
      "api_key": [
        {
          "current_key": "AIzaSyCxFrMH8HlpOmWZ0W6F6f8hNuz9ia2Bo5I"
        }
      ],
      "services": {
        "appinvite_service": {
          "other_platform_oauth_client": [
            {
              "client_id": "406572393086-j2mj3etu74timpbje8gathv8ggl7bnek.apps.googleusercontent.com",
              "client_type": 3
            }
          ]
        }
      }
    }
  ],
  "configuration_version": "1"
}